data/__init__.py
data/__init__.pyi
data/binary.py
data/load.py
data/util.py
medgnn_data-0.1.1.dist-info/METADATA
medgnn_data-0.1.1.dist-info/WHEEL
medgnn_data-0.1.1.dist-info/top_level.txt
medgnn_data-0.1.1.dist-info/RECORD
