Metadata-Version: 2.4
Name: medgnn-data
Version: 0.1.1
Summary: Medical tabular data
Author-email: Marcel Claramunt <marcel@marcelc.uk>
Project-URL: repo, https://github.com/marciclabas/medgnn.git
Requires-Python: >=3.10
Requires-Dist: scipy
Requires-Dist: numpy
Requires-Dist: scikit-learn
Requires-Dist: lazy-loader
